Metadata-Version: 2.1
Name: django-google-keys
Version: 0.0.3
Summary: Não é oficial do google
Author: issei momonge
Author-email: mggyggf@gmail.com
License: MIT License
Keywords: django key
License-File: LICENCE
